<Content>
    <DescriptionLevel>Item</DescriptionLevel>
    <Title>TR: Mot-cle : HOPITAL / LCI - 09/01/2009 - 12 H 15 - DISCOURS DE NICOLAS SARKOZY - 9 pages</Title>
    <OriginatingSystemId>&lt;AC005601rrZym1ZKCuJ0000c371@AC005603.ac.intranet.sante.gouv.fr&gt;</OriginatingSystemId>
    <Writer>
        <FullName>CAB-SJS-PRESSE</FullName>
        <Identifier>CAB-SJS-PRESSE@sante.gouv.fr</Identifier>
    </Writer>
    <Addressee>
        <FullName>ATTALI, Diane</FullName>
        <Identifier>Diane.ATTALI@sante.gouv.fr</Identifier>
    </Addressee>
    <Addressee>
        <FullName>BASSET, Marine</FullName>
        <Identifier>Marine.BASSET@sante-jeunesse-sports.gouv.fr</Identifier>
    </Addressee>
    <Addressee>
        <FullName>BILLAUD, Véronique</FullName>
        <Identifier>Veronique.BILLAUD@sante-jeunesse-sports.gouv.fr</Identifier>
    </Addressee>
    <Addressee>
        <FullName>BOYER, Olivier</FullName>
        <Identifier>Olivier.BOYER@sante.gouv.fr</Identifier>
    </Addressee>
    <Addressee>
        <FullName>BUBIEN, Yann</FullName>
        <Identifier>Yann.BUBIEN@sante-jeunesse-sports.gouv.fr</Identifier>
    </Addressee>
    <Addressee>
        <FullName>CAB-SJS-AFP</FullName>
        <Identifier>CAB-SJS-AFP@sante.gouv.fr</Identifier>
    </Addressee>
    <Addressee>
        <FullName>COUSIN, Marie-Alix</FullName>
        <Identifier>marie-alix.cousin@sante.gouv.fr</Identifier>
    </Addressee>
    <Addressee>
        <FullName>DE PROST, Yves</FullName>
        <Identifier>yves.deprost@sante.gouv.fr</Identifier>
    </Addressee>
    <Addressee>
        <FullName>DEGUELLE, Etienne</FullName>
        <Identifier>Etienne.DEGUELLE@sante-jeunesse-sports.gouv.fr</Identifier>
    </Addressee>
    <Addressee>
        <FullName>DENISSE, Lamiel</FullName>
        <Identifier>lamiel.denisse@sante.gouv.fr</Identifier>
    </Addressee>
    <Addressee>
        <FullName>DUFOUR, Mathias</FullName>
        <Identifier>Mathias.DUFOUR@sante-jeunesse-sports.gouv.fr</Identifier>
    </Addressee>
    <Addressee>
        <FullName>GUEPRATTE, Charles</FullName>
        <Identifier>Charles.GUEPRATTE@sante-jeunesse-sports.gouv.fr</Identifier>
    </Addressee>
    <Addressee>
        <FullName>LEMAIRE, François</FullName>
        <Identifier>Francois.LEMAIRE@sante-jeunesse-sports.gouv.fr</Identifier>
    </Addressee>
    <Addressee>
        <FullName>MANDRIN, Chimène</FullName>
        <Identifier>Chimene.MANDRIN@sante-jeunesse-sports.gouv.fr</Identifier>
    </Addressee>
    <Addressee>
        <FullName>MATILLON, Yves</FullName>
        <Identifier>Yves.MATILLON@sante-jeunesse-sports.gouv.fr</Identifier>
    </Addressee>
    <Addressee>
        <FullName>MOUNIER, Céline</FullName>
        <Identifier>celine.mounier@sante.gouv.fr</Identifier>
    </Addressee>
    <Addressee>
        <FullName>NABET, Norbert</FullName>
        <Identifier>Norbert.NABET@sante-jeunesse-sports.gouv.fr</Identifier>
    </Addressee>
    <Addressee>
        <FullName>NOELLEC, Béatrice</FullName>
        <Identifier>Beatrice.NOELLEC@sante-jeunesse-sports.gouv.fr</Identifier>
    </Addressee>
    <Addressee>
        <FullName>pauline buchet</FullName>
        <Identifier>pauline.buchet@sante.gouv.fr</Identifier>
    </Addressee>
    <Addressee>
        <FullName>RITTER, Philippe</FullName>
        <Identifier>Philippe.RITTER@sante-jeunesse-sports.gouv.fr</Identifier>
    </Addressee>
    <Addressee>
        <FullName>ROLLAND, Guillemette</FullName>
        <Identifier>Guillemette.ROLLAND@sante-jeunesse-sports.gouv.fr</Identifier>
    </Addressee>
    <SentDate>2009-01-12T10:07:39Z</SentDate>
    <ReceivedDate>2009-01-12T10:07:42Z</ReceivedDate>
    <TextContent>Bonne lecture
 
Chimène</TextContent>
</Content>